{"file":"blueDiamond.png","frames":{
"lz_nf1":{"x":90,"y":122,"w":25,"h":25,"offX":0,"offY":0,"sourceW":26,"sourceH":26},
"lz_hhe5":{"x":33,"y":34,"w":30,"h":29,"offX":0,"offY":1,"sourceW":30,"sourceH":32},
"lz_pt3":{"x":65,"y":93,"w":30,"h":27,"offX":0,"offY":2,"sourceW":30,"sourceH":32},
"lz_hh4":{"x":1,"y":34,"w":30,"h":29,"offX":0,"offY":1,"sourceW":30,"sourceH":32},
"lz_hh7":{"x":97,"y":33,"w":30,"h":29,"offX":0,"offY":1,"sourceW":30,"sourceH":32},
"lz_pte8":{"x":161,"y":92,"w":30,"h":27,"offX":0,"offY":2,"sourceW":30,"sourceH":32},
"lz_pt1":{"x":189,"y":121,"w":28,"h":25,"offX":1,"offY":3,"sourceW":30,"sourceH":32},
"lz_nf":{"x":63,"y":122,"w":25,"h":25,"offX":0,"offY":0,"sourceW":26,"sourceH":26},
"lz_hh9":{"x":33,"y":1,"w":30,"h":31,"offX":0,"offY":0,"sourceW":30,"sourceH":32},
"lz_pt4":{"x":33,"y":65,"w":30,"h":27,"offX":0,"offY":2,"sourceW":30,"sourceH":32},
"lz_hhe7":{"x":225,"y":32,"w":30,"h":29,"offX":0,"offY":1,"sourceW":30,"sourceH":32},
"lz_hh2":{"x":65,"y":1,"w":30,"h":30,"offX":0,"offY":1,"sourceW":30,"sourceH":32},
"lz_pte3":{"x":65,"y":64,"w":30,"h":27,"offX":0,"offY":2,"sourceW":30,"sourceH":32},
"lz_pt9":{"x":225,"y":63,"w":30,"h":27,"offX":0,"offY":2,"sourceW":30,"sourceH":32},
"lz_pte7":{"x":193,"y":63,"w":30,"h":27,"offX":0,"offY":2,"sourceW":30,"sourceH":32},
"lz_pte5":{"x":161,"y":63,"w":30,"h":27,"offX":0,"offY":2,"sourceW":30,"sourceH":32},
"lz_pt5":{"x":129,"y":63,"w":30,"h":27,"offX":0,"offY":2,"sourceW":30,"sourceH":32},
"lz_pt6":{"x":97,"y":93,"w":30,"h":27,"offX":0,"offY":2,"sourceW":30,"sourceH":32},
"lz_hh3":{"x":161,"y":32,"w":30,"h":29,"offX":0,"offY":1,"sourceW":30,"sourceH":32},
"lz_pt7":{"x":193,"y":92,"w":30,"h":27,"offX":0,"offY":2,"sourceW":30,"sourceH":32},
"lz_hh8":{"x":1,"y":1,"w":30,"h":31,"offX":0,"offY":0,"sourceW":30,"sourceH":32},
"lz_pt8":{"x":1,"y":65,"w":30,"h":27,"offX":0,"offY":2,"sourceW":30,"sourceH":32},
"lz_hhe9":{"x":225,"y":1,"w":30,"h":29,"offX":0,"offY":1,"sourceW":30,"sourceH":32},
"lz_hhe8":{"x":193,"y":1,"w":30,"h":29,"offX":0,"offY":1,"sourceW":30,"sourceH":32},
"lz_pt2":{"x":1,"y":94,"w":29,"h":27,"offX":0,"offY":2,"sourceW":30,"sourceH":32},
"lz_hhe2":{"x":97,"y":1,"w":30,"h":30,"offX":0,"offY":1,"sourceW":30,"sourceH":32},
"lz_pte6":{"x":97,"y":64,"w":30,"h":27,"offX":0,"offY":2,"sourceW":30,"sourceH":32},
"lz_pte4":{"x":225,"y":92,"w":30,"h":27,"offX":0,"offY":2,"sourceW":30,"sourceH":32},
"lz_pte1":{"x":219,"y":121,"w":28,"h":25,"offX":1,"offY":3,"sourceW":30,"sourceH":32},
"lz_hhe1":{"x":129,"y":121,"w":28,"h":27,"offX":1,"offY":2,"sourceW":30,"sourceH":32},
"lz_hh1":{"x":159,"y":121,"w":28,"h":27,"offX":1,"offY":2,"sourceW":30,"sourceH":32},
"lz_hh6":{"x":129,"y":1,"w":30,"h":29,"offX":0,"offY":1,"sourceW":30,"sourceH":32},
"lz_hhe3":{"x":65,"y":33,"w":30,"h":29,"offX":0,"offY":1,"sourceW":30,"sourceH":32},
"lz_hhe6":{"x":193,"y":32,"w":30,"h":29,"offX":0,"offY":1,"sourceW":30,"sourceH":32},
"lz_hh5":{"x":129,"y":32,"w":30,"h":29,"offX":0,"offY":1,"sourceW":30,"sourceH":32},
"lz_pte2":{"x":32,"y":94,"w":29,"h":27,"offX":0,"offY":2,"sourceW":30,"sourceH":32},
"lz_hhe4":{"x":161,"y":1,"w":30,"h":29,"offX":0,"offY":1,"sourceW":30,"sourceH":32},
"lz_pte9":{"x":129,"y":92,"w":30,"h":27,"offX":0,"offY":2,"sourceW":30,"sourceH":32},
"name_lz_hh4":{"x":211,"y":148,"w":20,"h":19,"offX":0,"offY":1,"sourceW":20,"sourceH":21},
"name_lz_hh5":{"x":189,"y":148,"w":20,"h":19,"offX":0,"offY":1,"sourceW":20,"sourceH":21},
"name_lz_hh6":{"x":23,"y":145,"w":20,"h":19,"offX":0,"offY":1,"sourceW":20,"sourceH":21},
"name_lz_hh7":{"x":1,"y":145,"w":20,"h":19,"offX":0,"offY":1,"sourceW":20,"sourceH":21},
"name_lz_hh8":{"x":23,"y":123,"w":20,"h":20,"offX":0,"offY":0,"sourceW":20,"sourceH":21},
"name_lz_hh9":{"x":1,"y":123,"w":20,"h":20,"offX":0,"offY":0,"sourceW":20,"sourceH":21},
"name_lz_nf":{"x":67,"y":149,"w":19,"h":19,"offX":0,"offY":1,"sourceW":20,"sourceH":21},
"name_lz_pt1":{"x":217,"y":169,"w":18,"h":17,"offX":1,"offY":3,"sourceW":20,"sourceH":21},
"name_lz_pt2":{"x":176,"y":169,"w":19,"h":18,"offX":0,"offY":2,"sourceW":20,"sourceH":21},
"name_lz_pt3":{"x":154,"y":150,"w":20,"h":18,"offX":0,"offY":2,"sourceW":20,"sourceH":21},
"name_lz_pt4":{"x":132,"y":150,"w":20,"h":18,"offX":0,"offY":2,"sourceW":20,"sourceH":21},
"name_lz_pt5":{"x":110,"y":150,"w":20,"h":18,"offX":0,"offY":2,"sourceW":20,"sourceH":21},
"name_lz_pt6":{"x":88,"y":149,"w":20,"h":18,"offX":0,"offY":2,"sourceW":20,"sourceH":21},
"name_lz_pt7":{"x":88,"y":169,"w":20,"h":18,"offX":0,"offY":2,"sourceW":20,"sourceH":21},
"name_lz_pt8":{"x":23,"y":166,"w":20,"h":18,"offX":0,"offY":2,"sourceW":20,"sourceH":21},
"name_lz_pt9":{"x":1,"y":166,"w":20,"h":18,"offX":0,"offY":2,"sourceW":20,"sourceH":21},
"name_lz_hh1":{"x":197,"y":169,"w":18,"h":18,"offX":1,"offY":1,"sourceW":20,"sourceH":21},
"name_lz_hh2":{"x":45,"y":149,"w":20,"h":19,"offX":0,"offY":1,"sourceW":20,"sourceH":21},
"name_lz_hh3":{"x":233,"y":148,"w":20,"h":19,"offX":0,"offY":1,"sourceW":20,"sourceH":21}}}